sssms/__init__.py
sssms/config.py
sssms/lookup.py
sssms/main.py
sssms/prx.py
sssms/sssmtp.py
sssms-0.3.4.dist-info/LICENSE
sssms-0.3.4.dist-info/METADATA
sssms-0.3.4.dist-info/WHEEL
sssms-0.3.4.dist-info/entry_points.txt
sssms-0.3.4.dist-info/top_level.txt
sssms-0.3.4.dist-info/RECORD
