Metadata-Version: 2.1
Name: sssms
Version: 0.3.4
Summary: Self-Service SMS via eMail
Home-page: https://github.com/schizoprada/sssms
Author: Joel Yisrael
Author-email: joel@sss.bot
Classifier: Programming Language :: Python :: 3
Classifier: License :: OSI Approved :: MIT License
Classifier: Operating System :: OS Independent
Requires-Python: >=3.6
License-File: LICENSE
Requires-Dist: click
Requires-Dist: requests
Requires-Dist: beautifulsoup4
Requires-Dist: rich
Requires-Dist: pyyaml
Requires-Dist: cryptography
Requires-Dist: proxy.py
